Atiny.py
__init__.py
test.py
atiny-0.0.4.dist-info/licenses/LICENSE
atiny-0.0.4.dist-info/METADATA
atiny-0.0.4.dist-info/WHEEL
atiny-0.0.4.dist-info/top_level.txt
atiny-0.0.4.dist-info/RECORD
