Metadata-Version: 2.4
Name: Atiny
Version: 0.0.4
Summary: Atiny is a gradient based PyTorch optimizer. Atiny uses half of Adam's memory to achieve results that are not inferior to Adam. 
Author-email: Psyche Halo <Psyche@WinsGod.com>
Project-URL: Homepage, https://github.com/PsycheHalo/Atiny
Project-URL: Issues, https://github.com/PsycheHalo/Atiny/issues
Keywords: tiny,Atiny,PyTorch,optimizer,AI,neural,NN,memory
Classifier: Programming Language :: Python :: 3
Classifier: Operating System :: OS Independent
Requires-Python: >=3.8
License-File: LICENSE
Requires-Dist: torch>=1.7.0
Dynamic: license-file
